{"collection":{"info":{"_postman_id":"aac1ba2c-1454-4a4a-9559-9d90990f7d49","name":"Hubspot APIs","schema":"https://schema.getpostman.com/json/collection/v2.1.0/collection.json","updatedAt":"2022-07-25T01:13:27.000Z","createdAt":"2022-07-25T01:12:48.000Z","lastUpdatedBy":"2333627","uid":"2333627-aac1ba2c-1454-4a4a-9559-9d90990f7d49"},"item":[],"event":[{"listen":"prerequest","script":{"id":"e7830c29-efa4-4efc-84ea-6379bb742f94","type":"text/javascript","exec":[""]}},{"listen":"test","script":{"id":"141cb3f1-deaf-4c21-8faf-a92ea63b04a2","type":"text/javascript","exec":[""]}}],"variable":[{"key":"Connection URL","value":"https://api.hubapi.com","type":"string"}]}}