{"collection":{"info":{"_postman_id":"ac3ff8c8-1378-4629-93c2-2bd04f0b1b78","name":"Google Healthcare","schema":"https://schema.getpostman.com/json/collection/v2.1.0/collection.json","updatedAt":"2022-10-20T04:45:22.000Z","createdAt":"2022-09-23T01:19:25.000Z","lastUpdatedBy":"2333627","uid":"2333627-ac3ff8c8-1378-4629-93c2-2bd04f0b1b78"},"item":[{"name":"Annotations","item":[{"name":"Create Annotation","id":"c541e118-9c93-43aa-811e-1c8f21f2f2c1","protocolProfileBehavior":{"disableBodyPruning":true},"request":{"method":"POST","header":[],"body":{"mode":"raw","raw":"{\r\n    \"name\": \"https://healthcare.googleapis.com/v1beta1/projects/healthcare-363401/locations/us-central1/datasets/starter-dataset/annotationStores/a.521/annotations/100\",\r\n    \"annotationSource\": {\r\n        \"cloudHealthcareSource\": {\r\n            \"name\": \"my-source\"\r\n        }\r\n    },\r\n    \"customData\": {\r\n        \"custom-1\": \"custom-data-1\",\r\n        \"custom-2\": \"custom-data-2\"\r\n    },\r\n    \"resourceAnnotation\": {\r\n        \"label\": \"A really good description\"\r\n    }\r\n}","options":{"raw":{"language":"json"}}},"url":{"raw":"https://healthcare.googleapis.com/v1beta1/projects/healthcare-363401/locations/us-central1/datasets/starter-dataset/annotationStores/a.521/annotations","protocol":"https","host":["healthcare","googleapis","com"],"path":["v1beta1","projects","healthcare-363401","locations","us-central1","datasets","starter-dataset","annotationStores","a.521","annotations"]}},"response":[],"uid":"2333627-c541e118-9c93-43aa-811e-1c8f21f2f2c1"},{"name":"AnnotationStores","id":"1a06cc77-b678-4c16-8037-c1d745236ee0","protocolProfileBehavior":{"disableBodyPruning":true},"request":{"method":"GET","header":[],"url":{"raw":"https://healthcare.googleapis.com/v1beta1/projects/healthcare-363401/locations/us-central1/datasets/starter-dataset/annotationStores","protocol":"https","host":["healthcare","googleapis","com"],"path":["v1beta1","projects","healthcare-363401","locations","us-central1","datasets","starter-dataset","annotationStores"]}},"response":[],"uid":"2333627-1a06cc77-b678-4c16-8037-c1d745236ee0"},{"name":"Create AnnotationStore","id":"57f6518f-7ab7-40fc-9f4b-ceb0df85b239","protocolProfileBehavior":{"disableBodyPruning":true},"request":{"method":"POST","header":[],"url":{"raw":"https://healthcare.googleapis.com/v1beta1/projects/healthcare-363401/locations/us-central1/datasets/starter-dataset/annotationStores?annotationStoreId=a.521","protocol":"https","host":["healthcare","googleapis","com"],"path":["v1beta1","projects","healthcare-363401","locations","us-central1","datasets","starter-dataset","annotationStores"],"query":[{"key":"annotationStoreId","value":"a.521","type":"text"}]}},"response":[],"uid":"2333627-57f6518f-7ab7-40fc-9f4b-ceb0df85b239"}],"id":"7a0e2dfe-3da8-40fd-812e-b3b93d5953f1","uid":"2333627-7a0e2dfe-3da8-40fd-812e-b3b93d5953f1"},{"name":"Consents","item":[{"name":"Create ConsentStore","id":"bd2aaf24-b072-4d7a-809d-b43b9fe4586b","protocolProfileBehavior":{"disableBodyPruning":true},"request":{"method":"POST","header":[],"url":{"raw":"https://healthcare.googleapis.com/v1beta1/projects/healthcare-363401/locations/us-central1/datasets/starter-dataset/consentStores?consentStoreId=b.654","protocol":"https","host":["healthcare","googleapis","com"],"path":["v1beta1","projects","healthcare-363401","locations","us-central1","datasets","starter-dataset","consentStores"],"query":[{"key":"consentStoreId","value":"b.654"}]}},"response":[],"uid":"2333627-bd2aaf24-b072-4d7a-809d-b43b9fe4586b"},{"name":"Check Data Access","id":"2f0610b8-2059-4579-af0d-f3e34cc2b309","protocolProfileBehavior":{"disableBodyPruning":true},"request":{"method":"POST","header":[],"body":{"mode":"raw","raw":"{\r\n  \"dataId\": \"some data id\",\r\n  \"requestAttributes\": {\r\n   \"name\": \"wrench\", \"mass\": \"1.3kg\", \"count\": \"3\"\r\n  }\r\n}","options":{"raw":{"language":"json"}}},"url":{"raw":"https://healthcare.googleapis.com/v1beta1/projects/healthcare-363401/locations/us-central1/datasets/starter-dataset/consentStores/b.654/checkDataAccess","protocol":"https","host":["healthcare","googleapis","com"],"path":["v1beta1","projects","healthcare-363401","locations","us-central1","datasets","starter-dataset","consentStores","b.654","checkDataAccess"],"query":[{"key":"consentStoreId","value":"b.654","disabled":true}]}},"response":[],"uid":"2333627-2f0610b8-2059-4579-af0d-f3e34cc2b309"}],"id":"ebe592d0-2980-43ce-bcc8-2ebe795a3b8a","uid":"2333627-ebe592d0-2980-43ce-bcc8-2ebe795a3b8a"},{"name":"Patient","item":[{"name":"Search for Patient","id":"82692552-cce2-465e-b652-e7432de63f65","protocolProfileBehavior":{"disableBodyPruning":true},"request":{"method":"GET","header":[],"url":{"raw":"https://healthcare.googleapis.com/v1beta1/projects/healthcare-363401/locations/us-central1/datasets/starter-dataset/fhirStores/s.841/fhir/Patient","protocol":"https","host":["healthcare","googleapis","com"],"path":["v1beta1","projects","healthcare-363401","locations","us-central1","datasets","starter-dataset","fhirStores","s.841","fhir","Patient"]}},"response":[],"uid":"2333627-82692552-cce2-465e-b652-e7432de63f65"},{"name":"Create Patient","id":"564daef1-5b7f-496a-9e7c-94245e87f350","protocolProfileBehavior":{"disableBodyPruning":true},"request":{"method":"POST","header":[{"key":"Content-Type","value":"application/fhir+json","type":"text"}],"body":{"mode":"raw","raw":"{\r\n    \"resourceType\": \"Patient\",\r\n    \"id\": \"example-id-101\",\r\n    \"text\": {\r\n        \"status\": \"generated\",\r\n        \"div\": \"<div xmlns=\\\"http://www.w3.org/1999/xhtml\\\">\\n\\t\\t\\t<table>\\n\\t\\t\\t\\t<tbody>\\n\\t\\t\\t\\t\\t<tr>\\n\\t\\t\\t\\t\\t\\t<td>Name</td>\\n\\t\\t\\t\\t\\t\\t<td>Peter James \\n              <b>Chalmers</b> (&quot;Jim&quot;)\\n            </td>\\n\\t\\t\\t\\t\\t</tr>\\n\\t\\t\\t\\t\\t<tr>\\n\\t\\t\\t\\t\\t\\t<td>Address</td>\\n\\t\\t\\t\\t\\t\\t<td>534 Erewhon, Pleasantville, Vic, 3999</td>\\n\\t\\t\\t\\t\\t</tr>\\n\\t\\t\\t\\t\\t<tr>\\n\\t\\t\\t\\t\\t\\t<td>Contacts</td>\\n\\t\\t\\t\\t\\t\\t<td>Home: unknown. Work: (03) 5555 6473</td>\\n\\t\\t\\t\\t\\t</tr>\\n\\t\\t\\t\\t\\t<tr>\\n\\t\\t\\t\\t\\t\\t<td>Id</td>\\n\\t\\t\\t\\t\\t\\t<td>MRN: 12345 (Acme Healthcare)</td>\\n\\t\\t\\t\\t\\t</tr>\\n\\t\\t\\t\\t</tbody>\\n\\t\\t\\t</table>\\n\\t\\t</div>\"\r\n    },\r\n    \"identifier\": [\r\n        {\r\n            \"use\": \"usual\",\r\n            \"type\": {\r\n                \"coding\": [\r\n                    {\r\n                        \"system\": \"http://terminology.hl7.org/CodeSystem/v2-0203\",\r\n                        \"code\": \"MR\"\r\n                    }\r\n                ]\r\n            },\r\n            \"system\": \"urn:oid:1.2.36.146.595.217.0.1\",\r\n            \"value\": \"12345\",\r\n            \"period\": {\r\n                \"start\": \"2001-05-06\"\r\n            },\r\n            \"assigner\": {\r\n                \"display\": \"Acme Healthcare\"\r\n            }\r\n        }\r\n    ],\r\n    \"active\": true,\r\n    \"name\": [\r\n        {\r\n            \"use\": \"official\",\r\n            \"family\": \"Chalmers\",\r\n            \"given\": [\r\n                \"Peter\",\r\n                \"James\"\r\n            ]\r\n        },\r\n        {\r\n            \"use\": \"usual\",\r\n            \"given\": [\r\n                \"Jim\"\r\n            ]\r\n        },\r\n        {\r\n            \"use\": \"maiden\",\r\n            \"family\": \"Windsor\",\r\n            \"given\": [\r\n                \"Peter\",\r\n                \"James\"\r\n            ],\r\n            \"period\": {\r\n                \"end\": \"2002\"\r\n            }\r\n        }\r\n    ],\r\n    \"telecom\": [\r\n        {\r\n            \"use\": \"home\"\r\n        },\r\n        {\r\n            \"system\": \"phone\",\r\n            \"value\": \"(03) 5555 6473\",\r\n            \"use\": \"work\",\r\n            \"rank\": 1\r\n        },\r\n        {\r\n            \"system\": \"phone\",\r\n            \"value\": \"(03) 3410 5613\",\r\n            \"use\": \"mobile\",\r\n            \"rank\": 2\r\n        },\r\n        {\r\n            \"system\": \"phone\",\r\n            \"value\": \"(03) 5555 8834\",\r\n            \"use\": \"old\",\r\n            \"period\": {\r\n                \"end\": \"2014\"\r\n            }\r\n        }\r\n    ],\r\n    \"gender\": \"male\",\r\n    \"birthDate\": \"1974-12-25\",\r\n    \"_birthDate\": {\r\n        \"extension\": [\r\n            {\r\n                \"url\": \"http://hl7.org/fhir/StructureDefinition/patient-birthTime\",\r\n                \"valueDateTime\": \"1974-12-25T14:35:45-05:00\"\r\n            }\r\n        ]\r\n    },\r\n    \"deceasedBoolean\": false,\r\n    \"address\": [\r\n        {\r\n            \"use\": \"home\",\r\n            \"type\": \"both\",\r\n            \"text\": \"534 Erewhon St PeasantVille, Rainbow, Vic  3999\",\r\n            \"line\": [\r\n                \"534 Erewhon St\"\r\n            ],\r\n            \"city\": \"PleasantVille\",\r\n            \"district\": \"Rainbow\",\r\n            \"state\": \"Vic\",\r\n            \"postalCode\": \"3999\",\r\n            \"period\": {\r\n                \"start\": \"1974-12-25\"\r\n            }\r\n        }\r\n    ],\r\n    \"contact\": [\r\n        {\r\n            \"relationship\": [\r\n                {\r\n                    \"coding\": [\r\n                        {\r\n                            \"system\": \"http://terminology.hl7.org/CodeSystem/v2-0131\",\r\n                            \"code\": \"N\"\r\n                        }\r\n                    ]\r\n                }\r\n            ],\r\n            \"name\": {\r\n                \"family\": \"du Marché\",\r\n                \"_family\": {\r\n                    \"extension\": [\r\n                        {\r\n                            \"url\": \"http://hl7.org/fhir/StructureDefinition/humanname-own-prefix\",\r\n                            \"valueString\": \"VV\"\r\n                        }\r\n                    ]\r\n                },\r\n                \"given\": [\r\n                    \"Bénédicte\"\r\n                ]\r\n            },\r\n            \"telecom\": [\r\n                {\r\n                    \"system\": \"phone\",\r\n                    \"value\": \"+33 (237) 998327\"\r\n                }\r\n            ],\r\n            \"address\": {\r\n                \"use\": \"home\",\r\n                \"type\": \"both\",\r\n                \"line\": [\r\n                    \"534 Erewhon St\"\r\n                ],\r\n                \"city\": \"PleasantVille\",\r\n                \"district\": \"Rainbow\",\r\n                \"state\": \"Vic\",\r\n                \"postalCode\": \"3999\",\r\n                \"period\": {\r\n                    \"start\": \"1974-12-25\"\r\n                }\r\n            },\r\n            \"gender\": \"female\",\r\n            \"period\": {\r\n                \"start\": \"2012\"\r\n            }\r\n        }\r\n    ],\r\n    \"managingOrganization\": null\r\n}","options":{"raw":{"language":"json"}}},"url":{"raw":"https://healthcare.googleapis.com/v1beta1/projects/healthcare-363401/locations/us-central1/datasets/starter-dataset/fhirStores/s.841/fhir/Patient","protocol":"https","host":["healthcare","googleapis","com"],"path":["v1beta1","projects","healthcare-363401","locations","us-central1","datasets","starter-dataset","fhirStores","s.841","fhir","Patient"]}},"response":[],"uid":"2333627-564daef1-5b7f-496a-9e7c-94245e87f350"}],"id":"53aa196f-78e6-41ca-a695-dd5b8b653cd1","uid":"2333627-53aa196f-78e6-41ca-a695-dd5b8b653cd1"},{"name":"FhirStores","item":[{"name":"Create FhirStore","id":"644aca3e-9afe-4ec9-a990-1016d1770de3","protocolProfileBehavior":{"disableBodyPruning":true},"request":{"method":"POST","header":[],"body":{"mode":"raw","raw":"{\r\n    \"name\": \"Fhir Store #1\",\r\n    \"enableUpdateCreate\": true,\r\n    \"notificationConfig\": null,\r\n    \"disableReferentialIntegrity\": false,\r\n    \"disableResourceVersioning\": false,\r\n    \"labels\": {\r\n        \"name\": \"wrench\",\r\n        \"mass\": \"13\",\r\n        \"count\": \"3\"\r\n    },\r\n    \"version\": \"R4\",\r\n    \"streamConfigs\": null,\r\n    \"validationConfig\": {\r\n        \"disableProfileValidation\": false,\r\n        \"enabledImplementationGuides\": null,\r\n        \"disableRequiredFieldValidation\": false,\r\n        \"disableReferenceTypeValidation\": false,\r\n        \"disableFhirpathValidation\": false\r\n    },\r\n    \"defaultSearchHandlingStrict\": true,\r\n    \"searchConfig\": null,\r\n    \"notificationConfigs\": null,\r\n    \"complexDataTypeReferenceParsing\": \"DISABLED\"\r\n}","options":{"raw":{"language":"json"}}},"url":{"raw":"https://healthcare.googleapis.com/v1beta1/projects/healthcare-363401/locations/us-central1/datasets/starter-dataset/fhirStores?fhirStoreId=s.841","protocol":"https","host":["healthcare","googleapis","com"],"path":["v1beta1","projects","healthcare-363401","locations","us-central1","datasets","starter-dataset","fhirStores"],"query":[{"key":"fhirStoreId","value":"s.841"}]}},"response":[],"uid":"2333627-644aca3e-9afe-4ec9-a990-1016d1770de3"},{"name":"Get FhirStores","id":"3942414f-c600-42fa-b58e-0d06d8383a00","protocolProfileBehavior":{"disableBodyPruning":true},"request":{"method":"GET","header":[],"body":{"mode":"raw","raw":"","options":{"raw":{"language":"json"}}},"url":{"raw":"https://healthcare.googleapis.com/v1beta1/projects/healthcare-363401/locations/us-central1/datasets/starter-dataset/fhirStores","protocol":"https","host":["healthcare","googleapis","com"],"path":["v1beta1","projects","healthcare-363401","locations","us-central1","datasets","starter-dataset","fhirStores"]}},"response":[],"uid":"2333627-3942414f-c600-42fa-b58e-0d06d8383a00"}],"id":"9d6debf1-eef3-4bd0-9f7f-d39808572ec8","uid":"2333627-9d6debf1-eef3-4bd0-9f7f-d39808572ec8"},{"name":"Invoice","item":[{"name":"Create Invoice","id":"a4f07f22-162f-43c6-84c5-da0df73bb642","protocolProfileBehavior":{"disableBodyPruning":true},"request":{"method":"POST","header":[{"key":"Content-Type","value":"application/fhir+json","type":"text"}],"body":{"mode":"raw","raw":"{\r\n  \"resourceType\": \"Invoice\",\r\n  \"id\": \"inv-1001\",\r\n  \"text\": {\r\n    \"status\": \"generated\",\r\n    \"div\": \"<div xmlns=\\\"http://www.w3.org/1999/xhtml\\\">Example of Invoice</div>\"\r\n  },\r\n  \"identifier\": [\r\n    {\r\n      \"system\": \"http://myHospital.org/Invoices\",\r\n      \"value\": \"654321\"\r\n    }\r\n  ],\r\n  \"status\": \"issued\",\r\n  \"subject\": {\r\n    \"reference\": \"Patient/9fe0075e-b9a9-41e8-a02d-3f02de159ca4\"\r\n  },\r\n  \"date\": \"2017-01-25T08:00:00+01:00\",\r\n  \"participant\": [\r\n    {\r\n      \"role\": {\r\n        \"coding\": [\r\n          {\r\n            \"system\": \"http://snomed.info/sct\",\r\n            \"code\": \"17561000\",\r\n            \"display\": \"Cardiologist\"\r\n          }\r\n        ]\r\n      },\r\n      \"actor\": {\r\n        \"reference\": \"Practitioner/be21896d-51b1-4b07-8854-909ad2f8ab10\"\r\n      }\r\n    }\r\n  ],\r\n  \"issuer\": {\r\n    \"identifier\": {\r\n      \"system\": \"http://myhospital/NamingSystem/departments\",\r\n      \"value\": \"CARD_INTERMEDIATE_CARE\"\r\n    }\r\n  },\r\n  \"account\": {\r\n    \"reference\": \"Account/1f796e90-aab8-4460-9040-13e31d5f683d\"\r\n  },\r\n  \"totalNet\": {\r\n    \"value\": 40,\r\n    \"currency\": \"EUR\"\r\n  },\r\n  \"totalGross\": {\r\n    \"value\": 48,\r\n    \"currency\": \"EUR\"\r\n  }\r\n}","options":{"raw":{"language":"json"}}},"url":{"raw":"https://healthcare.googleapis.com/v1beta1/projects/healthcare-363401/locations/us-central1/datasets/starter-dataset/fhirStores/s.841/fhir/Invoice","protocol":"https","host":["healthcare","googleapis","com"],"path":["v1beta1","projects","healthcare-363401","locations","us-central1","datasets","starter-dataset","fhirStores","s.841","fhir","Invoice"]}},"response":[],"uid":"2333627-a4f07f22-162f-43c6-84c5-da0df73bb642"},{"name":"Search for Invoices","id":"5ac04bf3-82de-4a8d-ab72-b610aa382e5f","protocolProfileBehavior":{"disableBodyPruning":true},"request":{"method":"GET","header":[],"url":{"raw":"https://healthcare.googleapis.com/v1beta1/projects/healthcare-363401/locations/us-central1/datasets/starter-dataset/fhirStores/s.841/fhir/Invoice","protocol":"https","host":["healthcare","googleapis","com"],"path":["v1beta1","projects","healthcare-363401","locations","us-central1","datasets","starter-dataset","fhirStores","s.841","fhir","Invoice"]}},"response":[],"uid":"2333627-5ac04bf3-82de-4a8d-ab72-b610aa382e5f"},{"name":"Create Invoice with Line Items","id":"819e7780-48ce-4691-bc6e-3b2a0fad35d3","protocolProfileBehavior":{"disableBodyPruning":true},"request":{"method":"POST","header":[{"key":"Content-Type","value":"application/fhir+json","type":"text"}],"body":{"mode":"raw","raw":"{\r\n    \"resourceType\": \"Invoice\",\r\n    \"id\": \"inv-1002\",\r\n    \"text\": {\r\n        \"status\": \"generated\",\r\n        \"div\": \"<div xmlns=\\\"http://www.w3.org/1999/xhtml\\\">Example of Invoice</div>\"\r\n    },\r\n    \"identifier\": [\r\n        {\r\n            \"system\": \"http://myHospital.org/Invoices\",\r\n            \"value\": \"654322\"\r\n        }\r\n    ],\r\n    \"status\": \"issued\",\r\n    \"subject\": {\r\n        \"reference\": \"Patient/9fe0075e-b9a9-41e8-a02d-3f02de159ca4\"\r\n    },\r\n    \"date\": \"2019-01-25T08:00:00+01:00\",\r\n    \"participant\": [\r\n        {\r\n            \"role\": {\r\n                \"coding\": [\r\n                    {\r\n                        \"system\": \"http://snomed.info/sct\",\r\n                        \"code\": \"17561000\",\r\n                        \"display\": \"Cardiologist\"\r\n                    }\r\n                ]\r\n            },\r\n            \"actor\": {\r\n                \"reference\": \"Practitioner/be21896d-51b1-4b07-8854-909ad2f8ab10\"\r\n            }\r\n        }\r\n    ],\r\n    \"issuer\": {\r\n        \"identifier\": {\r\n            \"system\": \"http://myhospital/NamingSystem/departments\",\r\n            \"value\": \"CARD_INTERMEDIATE_CARE\"\r\n        }\r\n    },\r\n    \"account\": {\r\n        \"reference\": \"Account/1f796e90-aab8-4460-9040-13e31d5f683d\"\r\n    },\r\n    \"lineItem\": [\r\n        {\r\n            \"sequence\": 10,\r\n            \"chargeItemCodeableConcept\": {\r\n                \"coding\": [\r\n                    {\r\n                        \"system\": \"http://snomed.info/sct\",\r\n                        \"code\": \"260385009\",\r\n                        \"display\": \"Negative\"\r\n                    },\r\n                    {\r\n                        \"system\": \"https://acme.lab/resultcodes\",\r\n                        \"code\": \"NEG\",\r\n                        \"display\": \"Negative\"\r\n                    }\r\n                ],\r\n                \"text\": \"Negative for Chlamydia Trachomatis rRNA\"\r\n            },\r\n            \"priceComponent\": [\r\n                {\r\n                    \"type\": \"base\",\r\n                    \"code\": {\r\n                        \"coding\": [\r\n                            {\r\n                                \"system\": \"http://snomed.info/sct\",\r\n                                \"code\": \"260385009\",\r\n                                \"display\": \"Negative\"\r\n                            },\r\n                            {\r\n                                \"system\": \"https://acme.lab/resultcodes\",\r\n                                \"code\": \"NEG\",\r\n                                \"display\": \"Negative\"\r\n                            }\r\n                        ],\r\n                        \"text\": \"Negative for Chlamydia Trachomatis rRNA\"\r\n                    },\r\n                    \"factor\": 1,\r\n                    \"amount\": {\r\n                        \"value\": 200,\r\n                        \"currency\": \"USD\"\r\n                    }\r\n                }\r\n            ]\r\n        }\r\n    ],\r\n    \"totalNet\": {\r\n        \"value\": 200,\r\n        \"currency\": \"USD\"\r\n    },\r\n    \"totalGross\": {\r\n        \"value\": 250,\r\n        \"currency\": \"USD\"\r\n    }\r\n}","options":{"raw":{"language":"json"}}},"url":{"raw":"https://healthcare.googleapis.com/v1beta1/projects/healthcare-363401/locations/us-central1/datasets/starter-dataset/fhirStores/s.841/fhir/Invoice","protocol":"https","host":["healthcare","googleapis","com"],"path":["v1beta1","projects","healthcare-363401","locations","us-central1","datasets","starter-dataset","fhirStores","s.841","fhir","Invoice"]}},"response":[],"uid":"2333627-819e7780-48ce-4691-bc6e-3b2a0fad35d3"}],"id":"3097d42f-9c94-429b-9a94-cd011f87ab42","uid":"2333627-3097d42f-9c94-429b-9a94-cd011f87ab42"},{"name":"Account","item":[{"name":"Create Account","id":"d54563bb-c8e9-4614-a3ec-f5fe3d3c2d3f","protocolProfileBehavior":{"disableBodyPruning":true},"request":{"method":"POST","header":[{"key":"Content-Type","value":"application/fhir+json","type":"text"}],"body":{"mode":"raw","raw":"{\r\n    \"resourceType\": \"Account\",\r\n    \"id\": \"acc-101\",\r\n    \"text\": {\r\n        \"status\": \"generated\",\r\n        \"div\": \"<div xmlns=\\\"http://www.w3.org/1999/xhtml\\\">HACC Funded Billing for Peter James Chalmers</div>\"\r\n    },\r\n    \"identifier\": [\r\n        {\r\n            \"system\": \"urn:oid:0.1.2.3.4.5.6.7\",\r\n            \"value\": \"654321\"\r\n        }\r\n    ],\r\n    \"status\": \"active\",\r\n    \"type\": {\r\n        \"coding\": [\r\n            {\r\n                \"system\": \"http://terminology.hl7.org/CodeSystem/v3-ActCode\",\r\n                \"code\": \"PBILLACCT\",\r\n                \"display\": \"patient billing account\"\r\n            }\r\n        ],\r\n        \"text\": \"patient\"\r\n    },\r\n    \"name\": \"HACC Funded Billing for Peter James Chalmers\",\r\n    \"subject\": [\r\n        {\r\n            \"reference\": \"Patient/9fe0075e-b9a9-41e8-a02d-3f02de159ca4\",\r\n            \"display\": \"Peter James Chalmers\"\r\n        }\r\n    ],\r\n    \"servicePeriod\": {\r\n        \"start\": \"2016-01-01\",\r\n        \"end\": \"2016-06-30\"\r\n    },\r\n    \"coverage\": [\r\n        {\r\n            \"coverage\": {\r\n                \"reference\": \"Coverage/0d5329c0-4ae9-48e0-9701-ddd87e973e5c\"\r\n            },\r\n            \"priority\": 1\r\n        }\r\n    ],\r\n    \"owner\": {\r\n        \"reference\": \"Organization/d9053304-82c7-4bba-8f03-cb845383ad0c\"\r\n    },\r\n    \"description\": \"Hospital charges\"\r\n}","options":{"raw":{"language":"json"}}},"url":{"raw":"https://healthcare.googleapis.com/v1beta1/projects/healthcare-363401/locations/us-central1/datasets/starter-dataset/fhirStores/s.841/fhir/Account","protocol":"https","host":["healthcare","googleapis","com"],"path":["v1beta1","projects","healthcare-363401","locations","us-central1","datasets","starter-dataset","fhirStores","s.841","fhir","Account"]}},"response":[],"uid":"2333627-d54563bb-c8e9-4614-a3ec-f5fe3d3c2d3f"}],"id":"df063a2e-64e2-451b-b9ac-eb10a1c667e6","uid":"2333627-df063a2e-64e2-451b-b9ac-eb10a1c667e6"},{"name":"Coverage","item":[{"name":"Create Coverage","id":"5a2a31c3-3af3-4b29-8db7-bf87d2b56976","protocolProfileBehavior":{"disableBodyPruning":true},"request":{"method":"POST","header":[{"key":"Content-Type","value":"application/fhir+json","type":"text"}],"body":{"mode":"raw","raw":"{\r\n    \"resourceType\": \"Coverage\",\r\n    \"id\": \"9876B1\",\r\n    \"text\": {\r\n        \"status\": \"generated\",\r\n        \"div\": \"<div xmlns=\\\"http://www.w3.org/1999/xhtml\\\">A human-readable rendering of the coverage</div>\"\r\n    },\r\n    \"identifier\": [\r\n        {\r\n            \"system\": \"http://benefitsinc.com/certificate\",\r\n            \"value\": \"12345\"\r\n        }\r\n    ],\r\n    \"status\": \"active\",\r\n    \"type\": {\r\n        \"coding\": [\r\n            {\r\n                \"system\": \"http://terminology.hl7.org/CodeSystem/v3-ActCode\",\r\n                \"code\": \"EHCPOL\",\r\n                \"display\": \"extended healthcare\"\r\n            }\r\n        ]\r\n    },\r\n    \"policyHolder\": {\r\n        \"reference\": \"http://benefitsinc.com/FHIR/Organization/CBI35\"\r\n    },\r\n    \"subscriber\": {\r\n        \"reference\": \"Patient/9fe0075e-b9a9-41e8-a02d-3f02de159ca4\"\r\n    },\r\n    \"beneficiary\": {\r\n        \"reference\": \"Patient/9fe0075e-b9a9-41e8-a02d-3f02de159ca4\"\r\n    },\r\n    \"dependent\": \"0\",\r\n    \"relationship\": {\r\n        \"coding\": [\r\n            {\r\n                \"code\": \"self\"\r\n            }\r\n        ]\r\n    },\r\n    \"period\": {\r\n        \"start\": \"2011-05-23\",\r\n        \"end\": \"2030-05-23\"\r\n    },\r\n    \"payor\": [\r\n        {\r\n            \"reference\": \"Organization/d9053304-82c7-4bba-8f03-cb845383ad0c\"\r\n        }\r\n    ],\r\n    \"class\": [\r\n        {\r\n            \"type\": {\r\n                \"coding\": [\r\n                    {\r\n                        \"system\": \"http://terminology.hl7.org/CodeSystem/coverage-class\",\r\n                        \"code\": \"group\"\r\n                    }\r\n                ]\r\n            },\r\n            \"value\": \"CB135\",\r\n            \"name\": \"Corporate Baker's Inc. Local #35\"\r\n        },\r\n        {\r\n            \"type\": {\r\n                \"coding\": [\r\n                    {\r\n                        \"system\": \"http://terminology.hl7.org/CodeSystem/coverage-class\",\r\n                        \"code\": \"subgroup\"\r\n                    }\r\n                ]\r\n            },\r\n            \"value\": \"123\",\r\n            \"name\": \"Trainee Part-time Benefits\"\r\n        },\r\n        {\r\n            \"type\": {\r\n                \"coding\": [\r\n                    {\r\n                        \"system\": \"http://terminology.hl7.org/CodeSystem/coverage-class\",\r\n                        \"code\": \"plan\"\r\n                    }\r\n                ]\r\n            },\r\n            \"value\": \"B37FC\",\r\n            \"name\": \"Full Coverage: Medical, Dental, Pharmacy, Vision, EHC\"\r\n        },\r\n        {\r\n            \"type\": {\r\n                \"coding\": [\r\n                    {\r\n                        \"system\": \"http://terminology.hl7.org/CodeSystem/coverage-class\",\r\n                        \"code\": \"subplan\"\r\n                    }\r\n                ]\r\n            },\r\n            \"value\": \"P7\",\r\n            \"name\": \"Includes afterlife benefits\"\r\n        },\r\n        {\r\n            \"type\": {\r\n                \"coding\": [\r\n                    {\r\n                        \"system\": \"http://terminology.hl7.org/CodeSystem/coverage-class\",\r\n                        \"code\": \"class\"\r\n                    }\r\n                ]\r\n            },\r\n            \"value\": \"SILVER\",\r\n            \"name\": \"Silver: Family Plan spouse only\"\r\n        },\r\n        {\r\n            \"type\": {\r\n                \"coding\": [\r\n                    {\r\n                        \"system\": \"http://terminology.hl7.org/CodeSystem/coverage-class\",\r\n                        \"code\": \"subclass\"\r\n                    }\r\n                ]\r\n            },\r\n            \"value\": \"Tier2\",\r\n            \"name\": \"Low deductable, max $20 copay\"\r\n        },\r\n        {\r\n            \"type\": {\r\n                \"coding\": [\r\n                    {\r\n                        \"system\": \"http://terminology.hl7.org/CodeSystem/coverage-class\",\r\n                        \"code\": \"sequence\"\r\n                    }\r\n                ]\r\n            },\r\n            \"value\": \"9\"\r\n        },\r\n        {\r\n            \"type\": {\r\n                \"coding\": [\r\n                    {\r\n                        \"system\": \"http://terminology.hl7.org/CodeSystem/coverage-class\",\r\n                        \"code\": \"rxid\"\r\n                    }\r\n                ]\r\n            },\r\n            \"value\": \"MDF12345\"\r\n        },\r\n        {\r\n            \"type\": {\r\n                \"coding\": [\r\n                    {\r\n                        \"system\": \"http://terminology.hl7.org/CodeSystem/coverage-class\",\r\n                        \"code\": \"rxbin\"\r\n                    }\r\n                ]\r\n            },\r\n            \"value\": \"987654\"\r\n        },\r\n        {\r\n            \"type\": {\r\n                \"coding\": [\r\n                    {\r\n                        \"system\": \"http://terminology.hl7.org/CodeSystem/coverage-class\",\r\n                        \"code\": \"rxgroup\"\r\n                    }\r\n                ]\r\n            },\r\n            \"value\": \"M35PT\"\r\n        },\r\n        {\r\n            \"type\": {\r\n                \"coding\": [\r\n                    {\r\n                        \"system\": \"http://terminology.hl7.org/CodeSystem/coverage-class\",\r\n                        \"code\": \"rxpcn\"\r\n                    }\r\n                ]\r\n            },\r\n            \"value\": \"234516\"\r\n        },\r\n        {\r\n            \"type\": {\r\n                \"coding\": [\r\n                    {\r\n                        \"system\": \"http://terminology.hl7.org/CodeSystem/coverage-class\",\r\n                        \"code\": \"sequence\"\r\n                    }\r\n                ]\r\n            },\r\n            \"value\": \"9\"\r\n        }\r\n    ]\r\n}","options":{"raw":{"language":"json"}}},"url":{"raw":"https://healthcare.googleapis.com/v1beta1/projects/healthcare-363401/locations/us-central1/datasets/starter-dataset/fhirStores/s.841/fhir/Coverage","protocol":"https","host":["healthcare","googleapis","com"],"path":["v1beta1","projects","healthcare-363401","locations","us-central1","datasets","starter-dataset","fhirStores","s.841","fhir","Coverage"]}},"response":[],"uid":"2333627-5a2a31c3-3af3-4b29-8db7-bf87d2b56976"}],"id":"d305211e-c037-4a5b-b03e-5504dc832bea","uid":"2333627-d305211e-c037-4a5b-b03e-5504dc832bea"},{"name":"Organization","item":[{"name":"Create Organization","id":"ae85c681-8f5a-4e18-918f-4a3d1652ccd9","protocolProfileBehavior":{"disableBodyPruning":true},"request":{"method":"POST","header":[{"key":"Content-Type","value":"application/fhir+json","type":"text"}],"body":{"mode":"raw","raw":"{\r\n    \"resourceType\": \"Organization\",\r\n    \"id\": \"3\",\r\n    \"text\": {\r\n        \"status\": \"generated\",\r\n        \"div\": \"<div xmlns=\\\"http://www.w3.org/1999/xhtml\\\">\\n      \\n      <p>XYZ Insurance</p>\\n    \\n    </div>\"\r\n    },\r\n    \"identifier\": [\r\n        {\r\n            \"system\": \"urn:oid:2.16.840.1.113883.3.19.2.4\",\r\n            \"value\": \"77777\"\r\n        }\r\n    ],\r\n    \"name\": \"Any Insurance\",\r\n    \"alias\": [\r\n        \"No Insurance\"\r\n    ]\r\n}","options":{"raw":{"language":"json"}}},"url":{"raw":"https://healthcare.googleapis.com/v1beta1/projects/healthcare-363401/locations/us-central1/datasets/starter-dataset/fhirStores/s.841/fhir/Organization","protocol":"https","host":["healthcare","googleapis","com"],"path":["v1beta1","projects","healthcare-363401","locations","us-central1","datasets","starter-dataset","fhirStores","s.841","fhir","Organization"]}},"response":[],"uid":"2333627-ae85c681-8f5a-4e18-918f-4a3d1652ccd9"}],"id":"10d94175-81ef-4a51-beb8-4b2a94a1316f","uid":"2333627-10d94175-81ef-4a51-beb8-4b2a94a1316f"},{"name":"Practitioner","item":[{"name":"Create Practitioner","id":"39a1398b-e034-4702-b56d-132d5f2146fe","protocolProfileBehavior":{"disableBodyPruning":true},"request":{"method":"POST","header":[{"key":"Content-Type","value":"application/fhir+json","type":"text"}],"body":{"mode":"raw","raw":"{\r\n    \"resourceType\": \"Practitioner\",\r\n    \"id\": \"dr-1001\",\r\n    \"text\": {\r\n        \"status\": \"generated\",\r\n        \"div\": \"<div xmlns=\\\"http://www.w3.org/1999/xhtml\\\">\\n      <p>Dr Adam Careful is a Referring Practitioner for Acme Hospital from 1-Jan 2012 to 31-Mar\\n        2012</p>\\n    </div>\"\r\n    },\r\n    \"identifier\": [\r\n        {\r\n            \"system\": \"http://www.acme.org/practitioners\",\r\n            \"value\": \"23\"\r\n        }\r\n    ],\r\n    \"active\": true,\r\n    \"name\": [\r\n        {\r\n            \"family\": \"Careful\",\r\n            \"given\": [\r\n                \"Adam\"\r\n            ],\r\n            \"prefix\": [\r\n                \"Dr\"\r\n            ]\r\n        }\r\n    ],\r\n    \"address\": [\r\n        {\r\n            \"use\": \"home\",\r\n            \"line\": [\r\n                \"534 Erewhon St\"\r\n            ],\r\n            \"city\": \"PleasantVille\",\r\n            \"state\": \"Vic\",\r\n            \"postalCode\": \"3999\"\r\n        }\r\n    ],\r\n    \"qualification\": [\r\n        {\r\n            \"identifier\": [\r\n                {\r\n                    \"system\": \"http://example.org/UniversityIdentifier\",\r\n                    \"value\": \"12345\"\r\n                }\r\n            ],\r\n            \"code\": {\r\n                \"coding\": [\r\n                    {\r\n                        \"system\": \"http://terminology.hl7.org/CodeSystem/v2-0360/2.7\",\r\n                        \"code\": \"BS\",\r\n                        \"display\": \"Bachelor of Science\"\r\n                    }\r\n                ],\r\n                \"text\": \"Bachelor of Science\"\r\n            },\r\n            \"period\": {\r\n                \"start\": \"1995\"\r\n            },\r\n            \"issuer\": {\r\n                \"display\": \"Example University\"\r\n            }\r\n        }\r\n    ]\r\n}","options":{"raw":{"language":"json"}}},"url":{"raw":"https://healthcare.googleapis.com/v1beta1/projects/healthcare-363401/locations/us-central1/datasets/starter-dataset/fhirStores/s.841/fhir/Practitioner","protocol":"https","host":["healthcare","googleapis","com"],"path":["v1beta1","projects","healthcare-363401","locations","us-central1","datasets","starter-dataset","fhirStores","s.841","fhir","Practitioner"]}},"response":[],"uid":"2333627-39a1398b-e034-4702-b56d-132d5f2146fe"}],"id":"f29cf4d6-5a9c-4f8b-bfb0-bfb4314523a6","uid":"2333627-f29cf4d6-5a9c-4f8b-bfb0-bfb4314523a6"},{"name":"Lookups","item":[{"name":"Contract Status","id":"1aa0f549-93e8-4ec2-955c-2bbb89545dfc","protocolProfileBehavior":{"disableBodyPruning":true},"request":{"method":"GET","header":[],"url":{"raw":"https://hl7.org/fhir/codesystem-contract-status.json","protocol":"https","host":["hl7","org"],"path":["fhir","codesystem-contract-status.json"]}},"response":[],"uid":"2333627-1aa0f549-93e8-4ec2-955c-2bbb89545dfc"},{"name":"Contract Status Another List","id":"2052ae9b-6b5a-417a-b565-3af5b3ff62ad","protocolProfileBehavior":{"disableBodyPruning":true},"request":{"auth":{"type":"noauth"},"method":"GET","header":[],"url":{"raw":"https://tx.fhir.org/r4/ValueSet/contract-status/$expand?display=disputed&_format=json","protocol":"https","host":["tx","fhir","org"],"path":["r4","ValueSet","contract-status","$expand"],"query":[{"key":"display","value":"disputed"},{"key":"_format","value":"json"}]}},"response":[],"uid":"2333627-2052ae9b-6b5a-417a-b565-3af5b3ff62ad"},{"name":"Claim Type","id":"0705861b-1d55-4520-a4d6-b5a81622214e","protocolProfileBehavior":{"disableBodyPruning":true},"request":{"method":"GET","header":[],"url":{"raw":"https://hl7.org/fhir/codesystem-claim-type.json","protocol":"https","host":["hl7","org"],"path":["fhir","codesystem-claim-type.json"]}},"response":[],"uid":"2333627-0705861b-1d55-4520-a4d6-b5a81622214e"}],"id":"053e3ff4-5c42-4a64-8b9e-60cc66dee0d5","uid":"2333627-053e3ff4-5c42-4a64-8b9e-60cc66dee0d5"},{"name":"Value Sets (for lookups)","item":[{"name":"Create Contract Statuses","id":"e8559bdb-a091-46d0-9a79-186ae2d1bff9","protocolProfileBehavior":{"disableBodyPruning":true},"request":{"method":"POST","header":[],"url":{"raw":"https://healthcare.googleapis.com/v1beta1/projects/healthcare-363401/locations/us-central1/datasets/starter-dataset/fhirStores/s.841/fhir/ValueSet","protocol":"https","host":["healthcare","googleapis","com"],"path":["v1beta1","projects","healthcare-363401","locations","us-central1","datasets","starter-dataset","fhirStores","s.841","fhir","ValueSet"]}},"response":[],"uid":"2333627-e8559bdb-a091-46d0-9a79-186ae2d1bff9"},{"name":"TX - Body Sites","id":"c6f06d14-e1da-49fc-8d46-a06150ac9985","protocolProfileBehavior":{"disableBodyPruning":true},"request":{"method":"GET","header":[]},"response":[],"uid":"2333627-c6f06d14-e1da-49fc-8d46-a06150ac9985"}],"id":"772eb94a-5074-4490-9d98-15c5f7b542c8","uid":"2333627-772eb94a-5074-4490-9d98-15c5f7b542c8"},{"name":"Locations","id":"7da44c20-d965-4954-b41e-fe7e0eee05af","protocolProfileBehavior":{"disableBodyPruning":true},"request":{"method":"GET","header":[],"url":{"raw":"https://healthcare.googleapis.com/v1beta1/projects/healthcare-363401/locations","protocol":"https","host":["healthcare","googleapis","com"],"path":["v1beta1","projects","healthcare-363401","locations"]}},"response":[],"uid":"2333627-7da44c20-d965-4954-b41e-fe7e0eee05af"},{"name":"Datasets","id":"bda67a91-a011-4f45-89b0-1ad29e99acb0","protocolProfileBehavior":{"disableBodyPruning":true},"request":{"method":"GET","header":[],"url":{"raw":"https://healthcare.googleapis.com/v1beta1/projects/healthcare-363401/locations/us-central1/datasets","protocol":"https","host":["healthcare","googleapis","com"],"path":["v1beta1","projects","healthcare-363401","locations","us-central1","datasets"]}},"response":[],"uid":"2333627-bda67a91-a011-4f45-89b0-1ad29e99acb0"}],"auth":{"type":"oauth2","oauth2":[{"key":"scope","value":"https://www.googleapis.com/auth/cloud-platform","type":"string"},{"key":"state","value":"","type":"string"},{"key":"accessTokenUrl","value":"https://accounts.google.com/o/oauth2/token","type":"string"},{"key":"authUrl","value":"https://accounts.google.com/o/oauth2/auth","type":"string"},{"key":"clientSecret","value":"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","type":"string"},{"key":"clientId","value":"194400860373-rom621r71mp308teqe0r7nntu62s92e9.apps.googleusercontent.com","type":"string"},{"key":"challengeAlgorithm","value":"S256","type":"string"},{"key":"useBrowser","value":true,"type":"boolean"},{"key":"redirect_uri","value":"{{re_directURI}}","type":"string"},{"key":"grant_type","value":"authorization_code","type":"string"},{"key":"addTokenTo","value":"header","type":"string"},{"key":"client_authentication","value":"body","type":"string"}]},"event":[{"listen":"prerequest","script":{"id":"2773ca37-9bbf-476a-b4b9-da58dc69f3e4","type":"text/javascript","exec":[""]}},{"listen":"test","script":{"id":"fa0d93af-6567-45ab-a1d7-79b265ce3f43","type":"text/javascript","exec":[""]}}]}}